LICENSE
README.md
pyproject.toml
setup.cfg
setup.py
src/tfe_run_wait/__init__.py
src/tfe_run_wait/apply.py
src/tfe_run_wait/argument_types.py
src/tfe_run_wait/cli.py
src/tfe_run_wait/logger.py
src/tfe_run_wait/wait.py
src/tfe_run_wait.egg-info/PKG-INFO
src/tfe_run_wait.egg-info/SOURCES.txt
src/tfe_run_wait.egg-info/dependency_links.txt
src/tfe_run_wait.egg-info/entry_points.txt
src/tfe_run_wait.egg-info/not-zip-safe
src/tfe_run_wait.egg-info/requires.txt
src/tfe_run_wait.egg-info/top_level.txt