Metadata-Version: 2.1
Name: tfe-run-wait
Version: 0.6.2
Summary: wait for a TFE run to complete
Home-page: https://github.com/binxio/tfe-run-wait
Author: Mark van Holsteijn
Author-email: markvanholsteijn@binx.io
License: BSD
Platform: any
Classifier: Development Status :: 4 - Beta
Classifier: Environment :: Console
Classifier: Intended Audience :: Developers
Classifier: License :: OSI Approved :: BSD License
Classifier: Operating System :: POSIX
Classifier: Operating System :: MacOS
Classifier: Operating System :: Unix
Classifier: Programming Language :: Python
Classifier: Programming Language :: Python :: 3
Classifier: Topic :: Software Development :: Libraries :: Python Modules
License-File: LICENSE
